{
  "jurisdiction": "PH",
  "section_id": "126",
  "title": ". Prohibition against injunction. No preliminary or permanent injunction or temporary restraining ",
  "content": ". Prohibition against injunction. No preliminary or permanent injunction or temporary restraining \norder may be issued by any court, tribunal or other entity against any proceedings before the Commission or \nthe Regional Boards. (As amended by Republic Act No. 6727, June 9, 1989)",
  "is_repealed": false,
  "metadata": {
    "source_file": "Labor-Code-of-the-Philippines-DOLE.pdf",
    "jurisdiction": "PH",
    "corpus_category": "general",
    "timestamp": "2026-01-21T14:28:37.786637"
  }
}