{
  "jurisdiction": "HK",
  "section_id": "38",
  "title": "Records to be produced to Commissioner",
  "content": "For the purposes of section 37, the Commissioner may, either \nby notice in writing served by registered post or by notice in the \nGazette, require any employer or class of employers to send to him \nall or any records of sickness days in respect of any period not \nexceeding 2 years preceding the date of the notice.\nLast updated date\n23.5.2025\nEmployment Ordinance\nPart VII\t\n7-38\nSection 38\t\nCap. 57\nVerified Copy\nPart VIII\nHolidays with Pay\n(Part VIII added 39 of 1973 s. 5. Format changes—E.R. 2 of 2012)",
  "is_repealed": false,
  "metadata": {
    "source_file": "Cap 57 Consolidated version for the Whole Chapter (24-08-2025) (English).pdf",
    "jurisdiction": "HK",
    "corpus_category": "contracts",
    "timestamp": "2026-01-21T14:28:34.213171"
  }
}