{
  "jurisdiction": "HK",
  "section_id": "15A",
  "title": "Offences",
  "content": "(1)\t\nAny employer who fails to—\n\t\n(a)\t\ngrant maternity leave;\n\t\n(b)\t\npay maternity leave pay in accordance with section 14; \nor (Amended 5 of 1995 s. 5)\n\t\n(c)\t\npay sickness allowance under section 33(3C),\nshall be guilty of an offence and shall be liable on conviction \nto a fine at level 5. (Amended 24 of 1988 s. 2; 103 of 1995 s. 4)\n\t\n(2)\t\nAny employer who, without any reasonable excuse, fails to \ncomply with—\n\t\n(a)\t\nthe requirements under section 15AA(2); or\n\t\n(b)\t\nthe determination made by the Commissioner under \nsection 15AA(6),\nshall be guilty of an offence and shall be liable on conviction \nto a fine at level 5. (Replaced 73 of 1997 s. 9)\n(Added 22 of 1981 s. 6)",
  "is_repealed": false,
  "metadata": {
    "source_file": "Cap 57 Consolidated version for the Whole Chapter (24-08-2025) (English).pdf",
    "jurisdiction": "HK",
    "corpus_category": "contracts",
    "timestamp": "2026-01-21T14:28:33.159801"
  }
}