{
  "jurisdiction": "PH",
  "section_id": "Sec. 11",
  "title": "Issuance of Closure Order",
  "content": "The POEA Administrator or the concerned DOLE Regional Director may conduct an ex parte preliminary examination to determine whether the activities of a non-licensee constitute a danger to national security and public order or will lead to further exploitation of job seekers. For this purpose, the POEA Administrator or the Regional Director concerned or their duly authorized representatives, may examine personally the complainants and/or their witnesses in the form of searching questions and answers and shall take their testimony under oath. The testimony of the complainants and/or witnesses shall be reduced in writing and signed by them and attested by an authorized officer.\n\nIf based on a surveillance report, or preliminary examination of the complainants, the POEA Administrator or DOLE Regional Director, or their authorized representative is satisfied that such danger or exploitation exists, a written order shall be issued by the POEA Administrator for the closure of the establishment being used for illegal recruitment activity.\n\nIn case of a business establishment whose license or permit to operate a business was issued by the local government, the Secretary of Labor and Employment, the POEA Administrator or the Regional Director concerned shall likewise recommend to the granting authority the immediate cancellation/revocation of the license or permit to operate its business.",
  "is_repealed": false,
  "metadata": {
    "source_file": "Omnibus IRR of RA 8042 as amended by RA 10022.pdf",
    "jurisdiction": "PH",
    "corpus_categories": [
      "wages",
      "contracts",
      "benefits",
      "general"
    ]
  }
}