{
  "jurisdiction": "HK",
  "section_id": "43S",
  "title": "Prosecution of offence under section 43P",
  "content": "(1)\t\nNo prosecution for an offence under section 43P may \nbe commenced without the consent in writing of the \nCommissioner.\n\t\n(2)\t\nBefore giving consent to prosecute under subsection (1), \nthe Commissioner must hear the person against whom the \nallegation is made, or give the person an opportunity of being \nheard.\n\t\n(3)\t\nSubject to subsection (1), a prosecution for an offence under \nsection 43P may be brought in the name of the Commissioner \nand may be commenced and conducted by any officer of the \nLabour Department authorized in that behalf in writing by the \nCommissioner.\n\t\n(4)\t\nNothing in this section derogates from the powers of the \nSecretary for Justice in respect of the prosecution of criminal \noffences.\nLast updated date\n19.10.2018\nEmployment Ordinance\nPart IXB\t\n9B-20\nSection 43S\t\nCap. 57\nVerified Copy\nPart X\nInformation respecting Conditions of Service\n(Amended 48 of 1984 s. 24)\n(Format changes—E.R. 3 of 2015)",
  "is_repealed": false,
  "metadata": {
    "source_file": "Cap 57 Consolidated version for the Whole Chapter (24-08-2025) (English).pdf",
    "jurisdiction": "HK",
    "corpus_category": "general",
    "timestamp": "2026-01-21T14:28:34.563025"
  }
}