{
  "jurisdiction": "HK",
  "section_id": "53",
  "title": "Refusal to issue, or revocation of, licences",
  "content": "(1)\t\nThe Commissioner may refuse to issue or renew a licence, \nor may revoke a licence, if he is satisfied on reasonable \ngrounds—\n\t\n(a)\t\nthat the name under which the employment agency is \noperated or is intended to be operated—\n\t\n(i)\t\nis identical with the name of another employment \nagency which is being, or has been, carried on by \nanother person; or\n\t\n(ii)\t\nso nearly resembles the name of another \nemployment agency as to be likely to deceive the \npublic;\n\t\n(b)\t\nthat the employment agency is being, or is likely to be, \nused for unlawful or immoral purposes; (Amended 8 of \n2018 s. 5)\n\t\n(c)\t\nthat the licensee or the person intending to be the \nlicensee— (Amended 8 of 2018 s. 5)\n\t\n(i)\t\nis an undischarged bankrupt;\n\t\n(ii)\t\nhas, within the preceding 5 years, been convicted \nof an offence against the person of a child, young \nperson or woman or of an offence involving \nmembership of a triad society, fraud, dishonesty or \nextortion;\n\t\n(iii)\t\nhas knowingly furnished to the Commissioner \nany false or misleading information in connection \nwith his application for the issue or renewal of the \nlicence;\nLast updated date\n24.8.2025\nEmployment Ordinance\nPart XII\t\n12-10\nSection 53\t\nCap. 57\nVerified Copy\n\t\n(iv)\t\nhas contravened any provision of this Part or any \nregulation made under section 62; (Amended 8 of \n2018 s. 5)\n\t\n(iva)\t\nhas not complied with a code of practice issued \nunder section 62A(1); or (Added 8 of 2018 s. 5)\n\t\n(v)\t\nis not, for any other reason, a fit and proper person \nto operate an employment agency; (Amended 8 of \n2018 s. 5)\n\t\n(d)\t\n(if the licensee or the person intending to be the licensee \nis a company or a partner in a partnership) that a related \nperson of the licensee or person—\n\t\n(i)\t\nhas, within the preceding 5 years, been convicted \nof an offence against the person of a child, young \nperson or woman or of an offence involving \nmembership of a triad society, fraud, dishonesty or \nextortion;\n\t\n(ii)\t\nhas contravened any provision of this Part or any \nregulation made under section 62; or\n\t\n(iii)\t\nhas not complied with a code of practice issued \nunder section 62A(1); or (Added 8 of 2018 s. 5)\n\t\n(e)\t\nthat an individual employed by the licensee or by the \nperson intending to be the licensee—\n\t\n(i)\t\nhas contravened any provision of this Part or any \nregulation made under section 62; or\n\t\n(ii)\t\nhas not complied with a code of practice issued \nunder section 62A(1). (Added 8 of 2018 s. 5)\n\t\n(2)\t\nThe Commissioner shall, if he refuses to issue or renew a \nlicence or revokes a licence, within 14 days after such refusal \nor revocation, notify the applicant or licensee in writing of \nthe grounds for such refusal or revocation.\nLast updated date\n24.8.2025\nEmployment Ordinance\nPart XII\t\n12-12\nSection 53\t\nCap. 57\nVerified Copy\n\t\n(3)\t\nAny person aggrieved by a decision of the Commissioner \ntaken in respect of him under subsection (1) may, within 28 \ndays after he is notified under subsection (2), appeal to the \nAdministrative Appeals Board. (Replaced 6 of 1994 s. 35)\n\t\n(4)\t\n(Repealed 6 of 1994 s. 35)\n\t\n(5)\t\nThe licensee shall, if the Commissioner refuses to renew or \nrevokes his licence under subsection (1),—\n\t\n(a)\t\nwithin 28 days after he is notified under subsection (2); \nor\n\t\n(b)\t\nif he has appealed under subsection (3), within 14 days \nafter he withdraws or abandons the appeal or he is \nnotified of the Administrative Appeals Board’s dismissal \nof the appeal,\ndeliver the licence, and every copy thereof, to the \nCommissioner. (Replaced 6 of 1994 s. 35)",
  "is_repealed": true,
  "metadata": {
    "source_file": "Cap 57 Consolidated version for the Whole Chapter (24-08-2025) (English).pdf",
    "jurisdiction": "HK",
    "corpus_category": "general",
    "timestamp": "2026-01-21T14:28:34.676623"
  }
}